dirsum/__init__.py
dirsum/cli/__init__.py
dirsum/cli/cli.py
dirsum/lib/__init__.py
dirsum/lib/filter_criteria.py
dirsum/lib/memory_utilities.py
dirsum/lib/parser.py
dirsum/lib/tree.py
dirsum-0.1.0.dist-info/WHEEL
dirsum-0.1.0.dist-info/entry_points.txt
dirsum-0.1.0.dist-info/LICENSE.txt
dirsum-0.1.0.dist-info/METADATA
dirsum-0.1.0.dist-info/RECORD
