Metadata-Version: 2.1
Name: dirsum
Version: 0.1.0
Summary: Directory summary tool.
Home-page: https://github.com/gregorybchris/dirsum
License: Apache Software License
Keywords: directory,file,summary
Author: Chris Gregory
Author-email: christopher.b.gregory@gmail.com
Requires-Python: >=3.9,<3.13
Classifier: Development Status :: 5 - Production/Stable
Classifier: Intended Audience :: Developers
Classifier: License :: OSI Approved :: Apache Software License
Classifier: License :: Other/Proprietary License
Classifier: Programming Language :: Python
Classifier: Programming Language :: Python :: 3
Classifier: Programming Language :: Python :: 3.9
Classifier: Programming Language :: Python :: 3.10
Classifier: Programming Language :: Python :: 3.11
Classifier: Programming Language :: Python :: 3.10
Classifier: Programming Language :: Python :: 3.11
Classifier: Programming Language :: Python :: 3.9
Classifier: Topic :: Software Development
Requires-Dist: click (>=8.1.7,<9.0.0)
Requires-Dist: colorama (>=0.4.6,<0.5.0)
Project-URL: Repository, https://github.com/gregorybchris/dirsum
